marios_candy_shop/__init__.py
marios_candy_shop/shop.py
marios_candy_shop-0.0.2.dist-info/METADATA
marios_candy_shop-0.0.2.dist-info/WHEEL
marios_candy_shop-0.0.2.dist-info/top_level.txt
marios_candy_shop-0.0.2.dist-info/RECORD
