Metadata-Version: 2.1
Name: marios_candy_shop
Version: 0.0.2
Home-page: 
Author: jacob.h.barrow
Author-email: jacob.h.barrow@gmail.com
License: MIT
Classifier: License :: OSI Approved :: MIT License
Classifier: Programming Language :: Python
Classifier: Programming Language :: Python :: 3
Requires-Dist: numpy
